{
  "annotations": {
    "list": []
  },
  "editable": true,
  "fiscalYearStartMonth": 0,
  "graphTooltip": 1,
  "links": [],
  "panels": [
    {
      "collapsed": false,
      "gridPos": { "h": 1, "w": 24, "x": 0, "y": 0 },
      "id": 100,
      "title": "Overview",
      "type": "row"
    },
    {
      "datasource": { "type": "prometheus", "uid": "${datasource}" },
      "fieldConfig": {
        "defaults": {
          "thresholds": {
            "mode": "absolute",
            "steps": [
              { "color": "red", "value": null },
              { "color": "green", "value": 1 }
            ]
          },
          "mappings": []
        }
      },
      "gridPos": { "h": 4, "w": 4, "x": 0, "y": 1 },
      "id": 1,
      "options": { "colorMode": "background", "graphMode": "none", "justifyMode": "auto", "textMode": "value_and_name", "reduceOptions": { "calcs": ["lastNotNull"] } },
      "title": "Workers Online",
      "type": "stat",
      "targets": [
        {
          "expr": "sum(worker_started)",
          "legendFormat": "Workers"
        }
      ]
    },
    {
      "datasource": { "type": "prometheus", "uid": "${datasource}" },
      "fieldConfig": {
        "defaults": {
          "thresholds": {
            "mode": "absolute",
            "steps": [
              { "color": "green", "value": null },
              { "color": "yellow", "value": 0.8 },
              { "color": "red", "value": 1 }
            ]
          }
        }
      },
      "gridPos": { "h": 4, "w": 4, "x": 4, "y": 1 },
      "id": 2,
      "options": { "colorMode": "background", "graphMode": "area", "justifyMode": "auto", "textMode": "value_and_name", "reduceOptions": { "calcs": ["lastNotNull"] } },
      "title": "Busy Workers",
      "type": "stat",
      "targets": [
        {
          "expr": "sum(worker_busy)",
          "legendFormat": "Busy"
        }
      ]
    },
    {
      "datasource": { "type": "prometheus", "uid": "${datasource}" },
      "fieldConfig": {
        "defaults": {
          "unit": "ops",
          "thresholds": {
            "mode": "absolute",
            "steps": [
              { "color": "green", "value": null }
            ]
          }
        }
      },
      "gridPos": { "h": 4, "w": 4, "x": 8, "y": 1 },
      "id": 3,
      "options": { "colorMode": "background", "graphMode": "area", "justifyMode": "auto", "textMode": "value_and_name", "reduceOptions": { "calcs": ["lastNotNull"] } },
      "title": "Jobs/sec",
      "type": "stat",
      "targets": [
        {
          "expr": "sum(rate(worker_execution_count[5m]))",
          "legendFormat": "Executions"
        }
      ]
    },
    {
      "datasource": { "type": "prometheus", "uid": "${datasource}" },
      "fieldConfig": {
        "defaults": {
          "unit": "ops",
          "thresholds": {
            "mode": "absolute",
            "steps": [
              { "color": "green", "value": null },
              { "color": "red", "value": 0.01 }
            ]
          }
        }
      },
      "gridPos": { "h": 4, "w": 4, "x": 12, "y": 1 },
      "id": 4,
      "options": { "colorMode": "background", "graphMode": "area", "justifyMode": "auto", "textMode": "value_and_name", "reduceOptions": { "calcs": ["lastNotNull"] } },
      "title": "Failed Jobs/sec",
      "type": "stat",
      "targets": [
        {
          "expr": "sum(rate(worker_execution_failed[5m]))",
          "legendFormat": "Failures"
        }
      ]
    },
    {
      "datasource": { "type": "prometheus", "uid": "${datasource}" },
      "fieldConfig": {
        "defaults": {
          "unit": "s",
          "thresholds": {
            "mode": "absolute",
            "steps": [
              { "color": "green", "value": null },
              { "color": "yellow", "value": 5 },
              { "color": "red", "value": 30 }
            ]
          }
        }
      },
      "gridPos": { "h": 4, "w": 4, "x": 16, "y": 1 },
      "id": 5,
      "options": { "colorMode": "background", "graphMode": "none", "justifyMode": "auto", "textMode": "value_and_name", "reduceOptions": { "calcs": ["lastNotNull"] } },
      "title": "P95 Execution Duration",
      "type": "stat",
      "targets": [
        {
          "expr": "histogram_quantile(0.95, sum(rate(worker_execution_duration_bucket[5m])) by (le))",
          "legendFormat": "p95"
        }
      ]
    },
    {
      "datasource": { "type": "prometheus", "uid": "${datasource}" },
      "fieldConfig": {
        "defaults": {
          "unit": "ops",
          "thresholds": {
            "mode": "absolute",
            "steps": [
              { "color": "blue", "value": null }
            ]
          }
        }
      },
      "gridPos": { "h": 4, "w": 4, "x": 20, "y": 1 },
      "id": 6,
      "options": { "colorMode": "background", "graphMode": "area", "justifyMode": "auto", "textMode": "value_and_name", "reduceOptions": { "calcs": ["lastNotNull"] } },
      "title": "Queue Throughput/sec",
      "type": "stat",
      "targets": [
        {
          "expr": "sum(rate(queue_push_count[5m]))",
          "legendFormat": "Enqueued"
        }
      ]
    },
    {
      "collapsed": false,
      "gridPos": { "h": 1, "w": 24, "x": 0, "y": 5 },
      "id": 101,
      "title": "Job Execution",
      "type": "row"
    },
    {
      "datasource": { "type": "prometheus", "uid": "${datasource}" },
      "fieldConfig": {
        "defaults": {
          "custom": { "lineWidth": 1, "fillOpacity": 20, "spanNulls": false, "stacking": { "mode": "none" } },
          "unit": "ops"
        }
      },
      "gridPos": { "h": 8, "w": 12, "x": 0, "y": 6 },
      "id": 10,
      "options": { "legend": { "displayMode": "table", "placement": "bottom", "calcs": ["mean", "max"] }, "tooltip": { "mode": "multi" } },
      "title": "Job Execution Rate",
      "type": "timeseries",
      "targets": [
        {
          "expr": "sum(rate(worker_execution_count[5m])) by (worker)",
          "legendFormat": "{{ name }}"
        }
      ]
    },
    {
      "datasource": { "type": "prometheus", "uid": "${datasource}" },
      "fieldConfig": {
        "defaults": {
          "custom": { "lineWidth": 1, "fillOpacity": 20, "spanNulls": false, "stacking": { "mode": "none" } },
          "unit": "ops"
        }
      },
      "gridPos": { "h": 8, "w": 12, "x": 12, "y": 6 },
      "id": 11,
      "options": { "legend": { "displayMode": "table", "placement": "bottom", "calcs": ["mean", "max"] }, "tooltip": { "mode": "multi" } },
      "title": "Failed Job Rate",
      "type": "timeseries",
      "targets": [
        {
          "expr": "sum(rate(worker_execution_failed[5m])) by (worker)",
          "legendFormat": "{{ name }}"
        }
      ]
    },
    {
      "datasource": { "type": "prometheus", "uid": "${datasource}" },
      "fieldConfig": {
        "defaults": {
          "custom": { "lineWidth": 1, "fillOpacity": 10, "spanNulls": false },
          "unit": "s"
        }
      },
      "gridPos": { "h": 8, "w": 12, "x": 0, "y": 14 },
      "id": 12,
      "options": { "legend": { "displayMode": "table", "placement": "bottom", "calcs": ["mean", "max"] }, "tooltip": { "mode": "multi" } },
      "title": "Execution Duration Percentiles",
      "type": "timeseries",
      "targets": [
        {
          "expr": "histogram_quantile(0.50, sum(rate(worker_execution_duration_bucket[5m])) by (le))",
          "legendFormat": "p50"
        },
        {
          "expr": "histogram_quantile(0.90, sum(rate(worker_execution_duration_bucket[5m])) by (le))",
          "legendFormat": "p90"
        },
        {
          "expr": "histogram_quantile(0.95, sum(rate(worker_execution_duration_bucket[5m])) by (le))",
          "legendFormat": "p95"
        },
        {
          "expr": "histogram_quantile(0.99, sum(rate(worker_execution_duration_bucket[5m])) by (le))",
          "legendFormat": "p99"
        }
      ]
    },
    {
      "datasource": { "type": "prometheus", "uid": "${datasource}" },
      "fieldConfig": {
        "defaults": {
          "custom": { "lineWidth": 1, "fillOpacity": 10, "spanNulls": false },
          "unit": "s"
        }
      },
      "gridPos": { "h": 8, "w": 12, "x": 12, "y": 14 },
      "id": 13,
      "options": { "legend": { "displayMode": "table", "placement": "bottom", "calcs": ["mean", "max"] }, "tooltip": { "mode": "multi" } },
      "title": "Queue Pull Duration Percentiles",
      "type": "timeseries",
      "targets": [
        {
          "expr": "histogram_quantile(0.50, sum(rate(worker_pull_duration_bucket[5m])) by (le))",
          "legendFormat": "p50"
        },
        {
          "expr": "histogram_quantile(0.95, sum(rate(worker_pull_duration_bucket[5m])) by (le))",
          "legendFormat": "p95"
        },
        {
          "expr": "histogram_quantile(0.99, sum(rate(worker_pull_duration_bucket[5m])) by (le))",
          "legendFormat": "p99"
        }
      ]
    },
    {
      "collapsed": false,
      "gridPos": { "h": 1, "w": 24, "x": 0, "y": 22 },
      "id": 102,
      "title": "Queue",
      "type": "row"
    },
    {
      "datasource": { "type": "prometheus", "uid": "${datasource}" },
      "fieldConfig": {
        "defaults": {
          "custom": { "lineWidth": 1, "fillOpacity": 20, "spanNulls": false, "stacking": { "mode": "normal" } },
          "unit": "short"
        }
      },
      "gridPos": { "h": 8, "w": 12, "x": 0, "y": 23 },
      "id": 20,
      "options": { "legend": { "displayMode": "table", "placement": "bottom", "calcs": ["mean", "max", "lastNotNull"] }, "tooltip": { "mode": "multi" } },
      "title": "Queue Operations Rate",
      "type": "timeseries",
      "targets": [
        {
          "expr": "sum(rate(queue_push_count[5m]))",
          "legendFormat": "Pushed"
        },
        {
          "expr": "sum(rate(queue_pull_count[5m]))",
          "legendFormat": "Pulled"
        },
        {
          "expr": "sum(rate(queue_delete_count[5m]))",
          "legendFormat": "Deleted"
        }
      ]
    },
    {
      "datasource": { "type": "prometheus", "uid": "${datasource}" },
      "fieldConfig": {
        "defaults": {
          "custom": { "lineWidth": 1, "fillOpacity": 20, "spanNulls": false },
          "unit": "short"
        }
      },
      "gridPos": { "h": 8, "w": 12, "x": 12, "y": 23 },
      "id": 21,
      "options": { "legend": { "displayMode": "table", "placement": "bottom", "calcs": ["mean", "max", "lastNotNull"] }, "tooltip": { "mode": "multi" } },
      "title": "Queue Depth by Tag",
      "type": "timeseries",
      "targets": [
        {
          "expr": "queue_count",
          "legendFormat": "{{ tag }}"
        }
      ]
    },
    {
      "datasource": { "type": "prometheus", "uid": "${datasource}" },
      "fieldConfig": {
        "defaults": {
          "custom": { "lineWidth": 1, "fillOpacity": 20, "spanNulls": false },
          "unit": "short"
        }
      },
      "gridPos": { "h": 8, "w": 12, "x": 0, "y": 31 },
      "id": 22,
      "options": { "legend": { "displayMode": "table", "placement": "bottom", "calcs": ["mean", "max", "lastNotNull"] }, "tooltip": { "mode": "multi" } },
      "title": "Running Jobs by Tag",
      "type": "timeseries",
      "targets": [
        {
          "expr": "queue_running_count",
          "legendFormat": "{{ tag }}"
        }
      ]
    },
    {
      "datasource": { "type": "prometheus", "uid": "${datasource}" },
      "fieldConfig": {
        "defaults": {
          "custom": { "lineWidth": 1, "fillOpacity": 10, "spanNulls": false },
          "unit": "short"
        }
      },
      "gridPos": { "h": 8, "w": 12, "x": 12, "y": 31 },
      "id": 23,
      "options": { "legend": { "displayMode": "table", "placement": "bottom", "calcs": ["sum"] }, "tooltip": { "mode": "multi" } },
      "title": "Zombie Jobs (Restarts / Deletes)",
      "type": "timeseries",
      "targets": [
        {
          "expr": "rate(queue_zombie_restart_count[5m])",
          "legendFormat": "Zombie Restarts"
        },
        {
          "expr": "rate(queue_zombie_delete_count[5m])",
          "legendFormat": "Zombie Deletes"
        }
      ]
    },
    {
      "collapsed": false,
      "gridPos": { "h": 1, "w": 24, "x": 0, "y": 31 },
      "id": 103,
      "title": "Workers",
      "type": "row"
    },
    {
      "datasource": { "type": "prometheus", "uid": "${datasource}" },
      "fieldConfig": {
        "defaults": {
          "custom": { "lineWidth": 1, "fillOpacity": 30, "spanNulls": false, "stacking": { "mode": "normal" } },
          "unit": "short"
        }
      },
      "gridPos": { "h": 8, "w": 12, "x": 0, "y": 32 },
      "id": 30,
      "options": { "legend": { "displayMode": "table", "placement": "bottom", "calcs": ["mean", "max", "lastNotNull"] }, "tooltip": { "mode": "multi" } },
      "title": "Worker Status",
      "type": "timeseries",
      "targets": [
        {
          "expr": "sum(worker_started)",
          "legendFormat": "Started"
        },
        {
          "expr": "sum(worker_busy)",
          "legendFormat": "Busy"
        }
      ]
    },
    {
      "datasource": { "type": "prometheus", "uid": "${datasource}" },
      "fieldConfig": {
        "defaults": {
          "custom": { "lineWidth": 1, "fillOpacity": 20, "spanNulls": false },
          "unit": "short"
        }
      },
      "gridPos": { "h": 8, "w": 12, "x": 12, "y": 32 },
      "id": 31,
      "options": { "legend": { "displayMode": "table", "placement": "bottom", "calcs": ["mean", "max"] }, "tooltip": { "mode": "multi" } },
      "title": "Worker Busy State (per worker)",
      "type": "timeseries",
      "targets": [
        {
          "expr": "worker_busy",
          "legendFormat": "{{ name }}"
        }
      ]
    },
    {
      "datasource": { "type": "prometheus", "uid": "${datasource}" },
      "fieldConfig": {
        "defaults": {
          "custom": { "lineWidth": 1, "fillOpacity": 10, "spanNulls": false },
          "unit": "s"
        }
      },
      "gridPos": { "h": 8, "w": 24, "x": 0, "y": 40 },
      "id": 32,
      "options": { "legend": { "displayMode": "table", "placement": "bottom", "calcs": ["mean", "max"] }, "tooltip": { "mode": "multi" } },
      "title": "Job Save Duration Percentiles",
      "type": "timeseries",
      "targets": [
        {
          "expr": "histogram_quantile(0.50, sum(rate(worker_save_duration_bucket[5m])) by (le))",
          "legendFormat": "p50"
        },
        {
          "expr": "histogram_quantile(0.95, sum(rate(worker_save_duration_bucket[5m])) by (le))",
          "legendFormat": "p95"
        },
        {
          "expr": "histogram_quantile(0.99, sum(rate(worker_save_duration_bucket[5m])) by (le))",
          "legendFormat": "p99"
        }
      ]
    },
    {
      "collapsed": false,
      "gridPos": { "h": 1, "w": 24, "x": 0, "y": 48 },
      "id": 104,
      "title": "Health & Database",
      "type": "row"
    },
    {
      "datasource": { "type": "prometheus", "uid": "${datasource}" },
      "fieldConfig": {
        "defaults": {
          "thresholds": {
            "mode": "absolute",
            "steps": [
              { "color": "green", "value": null },
              { "color": "yellow", "value": 50 },
              { "color": "red", "value": 200 }
            ]
          },
          "unit": "ms"
        }
      },
      "gridPos": { "h": 4, "w": 6, "x": 0, "y": 49 },
      "id": 40,
      "options": { "colorMode": "background", "graphMode": "area", "justifyMode": "auto", "textMode": "value_and_name", "reduceOptions": { "calcs": ["lastNotNull"] } },
      "title": "DB Latency",
      "type": "stat",
      "targets": [
        {
          "expr": "health_database_latency_ms",
          "legendFormat": "Latency"
        }
      ]
    },
    {
      "datasource": { "type": "prometheus", "uid": "${datasource}" },
      "fieldConfig": {
        "defaults": {
          "thresholds": {
            "mode": "absolute",
            "steps": [
              { "color": "green", "value": null },
              { "color": "red", "value": 1 }
            ]
          },
          "mappings": [
            { "options": { "0": { "text": "OK" }, "1": { "text": "UNRESPONSIVE" } }, "type": "value" }
          ]
        }
      },
      "gridPos": { "h": 4, "w": 6, "x": 6, "y": 49 },
      "id": 41,
      "options": { "colorMode": "background", "graphMode": "none", "justifyMode": "auto", "textMode": "value_and_name", "reduceOptions": { "calcs": ["lastNotNull"] } },
      "title": "DB Responsive",
      "type": "stat",
      "targets": [
        {
          "expr": "health_database_unresponsive",
          "legendFormat": "DB"
        }
      ]
    },
    {
      "datasource": { "type": "prometheus", "uid": "${datasource}" },
      "fieldConfig": {
        "defaults": {
          "unit": "short",
          "thresholds": {
            "mode": "absolute",
            "steps": [
              { "color": "green", "value": null }
            ]
          }
        }
      },
      "gridPos": { "h": 4, "w": 6, "x": 12, "y": 49 },
      "id": 42,
      "options": { "colorMode": "background", "graphMode": "none", "justifyMode": "auto", "textMode": "value_and_name", "reduceOptions": { "calcs": ["lastNotNull"] } },
      "title": "DB Pool Size",
      "type": "stat",
      "targets": [
        {
          "expr": "health_database_pool_size",
          "legendFormat": "Current"
        }
      ]
    },
    {
      "datasource": { "type": "prometheus", "uid": "${datasource}" },
      "fieldConfig": {
        "defaults": {
          "custom": { "lineWidth": 1, "fillOpacity": 20, "spanNulls": false },
          "unit": "short"
        }
      },
      "gridPos": { "h": 8, "w": 12, "x": 0, "y": 53 },
      "id": 43,
      "options": { "legend": { "displayMode": "table", "placement": "bottom", "calcs": ["mean", "max", "lastNotNull"] }, "tooltip": { "mode": "multi" } },
      "title": "Database Connection Pool",
      "type": "timeseries",
      "targets": [
        {
          "expr": "pool_connections_active",
          "legendFormat": "Active"
        },
        {
          "expr": "pool_connections_idle",
          "legendFormat": "Idle"
        },
        {
          "expr": "pool_connections_max",
          "legendFormat": "Max"
        }
      ]
    },
    {
      "datasource": { "type": "prometheus", "uid": "${datasource}" },
      "fieldConfig": {
        "defaults": {
          "custom": { "lineWidth": 1, "fillOpacity": 10, "spanNulls": false },
          "unit": "ms"
        }
      },
      "gridPos": { "h": 8, "w": 12, "x": 12, "y": 53 },
      "id": 44,
      "options": { "legend": { "displayMode": "table", "placement": "bottom", "calcs": ["mean", "max"] }, "tooltip": { "mode": "multi" } },
      "title": "Database Latency Over Time",
      "type": "timeseries",
      "targets": [
        {
          "expr": "health_database_latency_ms",
          "legendFormat": "DB Latency"
        }
      ]
    }
  ],
  "schemaVersion": 39,
  "tags": ["windmill", "automation"],
  "templating": {
    "list": [
      {
        "current": { "selected": false, "text": "Prometheus", "value": "prometheus" },
        "hide": 0,
        "includeAll": false,
        "label": "Data Source",
        "multi": false,
        "name": "datasource",
        "options": [],
        "query": "prometheus",
        "refresh": 1,
        "type": "datasource"
      }
    ]
  },
  "time": { "from": "now-6h", "to": "now" },
  "timepicker": {},
  "timezone": "",
  "title": "Windmill",
  "uid": "windmill",
  "version": 1
}
